{
    "sleep_times": {
        "min": 2,
        "max": 4
    },
    "api_settings": {
        "job_decoration_id": "com.linkedin.voyager.deco.jobs.web.shared.WebFullJobPosting-65",
        "number_of_pages": 1
    },
    "search_params": {
        "keywords": "Data Analyst",
        "location_name": "Australia",
        "limit": 20,
        "listed_at": 86400,  
        "_comment": "listed_at = days * 24 * 60 * 60"
    },
    "accounts": {
        "account2": {
            "email": "data15group3@gmail.com",
            "cookie_file": "data15group3@gmail.com.jr"
        },
        "account1": {
            "email": "ron87190@gmail.com",
            "cookie_file": "ron87190@gmail.com.jr"
        },
        "account3": {
            "email": "elizkoko07@gmail.com",
            "cookie_file": "elizkoko07@gmail.com.jr"
        }
    }
}